{"Name":"A","RollNumber":"1","BirthDate":"01-01-1990","MathMarks":"4","ChemistryMarks":"5","PhysicsMarks":"6","EnglishMarks":"8"}
{"Name":"B","RollNumber":"2","BirthDate":"02-01-1990","MathMarks":"5","ChemistryMarks":"6","PhysicsMarks":"8","EnglishMarks":"9"}
{"Name":"C","RollNumber":"3","BirthDate":"03-01-1990","MathMarks":"5","ChemistryMarks":"6","PhysicsMarks":"8","EnglishMarks":"4"}
{"Name":"C","RollNumber":"3","BirthDate":"03-01-1990","MathMarks":"4","ChemistryMarks":"5","PhysicsMarks":"6","EnglishMarks":"8"}
{"Name":"C","RollNumber":"3","BirthDate":"03-01-1990","MathMarks":"4","ChemistryMarks":"5","PhysicsMarks":"6","EnglishMarks":"8"}
{"Name":"C","RollNumber":"3","BirthDate":"03-01-1990","MathMarks":"4","ChemistryMarks":"5","PhysicsMarks":"68","EnglishMarks":"5"}
